graphrox/__init__.py
graphrox/graphrox-aarch64-apple-darwin.dylib
graphrox/graphrox-aarch64-unknown-linux-gnu.so
graphrox/graphrox-aarch64-w64.dll
graphrox/graphrox-x86_64-apple-darwin.dylib
graphrox/graphrox-x86_64-unknown-linux-gnu.so
graphrox/graphrox-x86_64-w64.dll
graphrox-1.2.0.dist-info/LICENSE
graphrox-1.2.0.dist-info/METADATA
graphrox-1.2.0.dist-info/WHEEL
graphrox-1.2.0.dist-info/top_level.txt
graphrox-1.2.0.dist-info/RECORD
