Metadata-Version: 2.1
Name: graphrox
Version: 1.2.0
Summary: A network graph library for efficiently compressing and generating approximations of graphs
Author: Tanner Davies
License: MIT License
Keywords: machine learning,graph,graphs,graph approximation,compression,graph compression
Requires-Python: >=3.4
License-File: LICENSE
